aseprite_reader/__init__.py
aseprite_reader/aseprite_file.py
aseprite_reader/chunk.py
aseprite_reader/composite.py
aseprite_reader/frame.py
aseprite_reader/header.py
aseprite_reader/render.py
aseprite_reader/utils.py
aseprite_reader/chunks/__init__.py
aseprite_reader/chunks/cel_chunk.py
aseprite_reader/chunks/cel_extra_chunk.py
aseprite_reader/chunks/color_profile_chunk.py
aseprite_reader/chunks/external_files_chunk.py
aseprite_reader/chunks/layer_chunk.py
aseprite_reader/chunks/mask_chunk.py
aseprite_reader/chunks/old_palette_chunk_04.py
aseprite_reader/chunks/old_palette_chunk_11.py
aseprite_reader/chunks/palette_chunk.py
aseprite_reader/chunks/path_chunk.py
aseprite_reader/chunks/slice_chunk.py
aseprite_reader/chunks/tags_chunk.py
aseprite_reader/chunks/tileset_chunk.py
aseprite_reader/chunks/user_data_chunk.py
aseprite_reader/models/__init__.py
aseprite_reader/models/external_file.py
aseprite_reader/models/palette_color.py
aseprite_reader/models/slice_key.py
aseprite_reader/models/tag.py
aseprite_reader-1.0.0.post1.dist-info/METADATA
aseprite_reader-1.0.0.post1.dist-info/WHEEL
aseprite_reader-1.0.0.post1.dist-info/licenses/LICENSE
aseprite_reader-1.0.0.post1.dist-info/RECORD
